codemod_pip_requirements/__init__.py
codemod_pip_requirements-0.0.0a1.dist-info/METADATA
codemod_pip_requirements-0.0.0a1.dist-info/WHEEL
codemod_pip_requirements-0.0.0a1.dist-info/RECORD
